refresher/__init__.py
refresher/__main__.py
refresher/refresher.py
PowerBI_refresher_NPP-1.1.9.dist-info/LICENSE
PowerBI_refresher_NPP-1.1.9.dist-info/METADATA
PowerBI_refresher_NPP-1.1.9.dist-info/WHEEL
PowerBI_refresher_NPP-1.1.9.dist-info/entry_points.txt
PowerBI_refresher_NPP-1.1.9.dist-info/top_level.txt
PowerBI_refresher_NPP-1.1.9.dist-info/RECORD
